tecoroute/__init__.py
tecoroute/__main__.py
tecoroute/_cli.py
tecoroute/_http.py
tecoroute/_misc.py
tecoroute/connector.py
tecoroute-0.1.0.dist-info/LICENSE
tecoroute-0.1.0.dist-info/METADATA
tecoroute-0.1.0.dist-info/WHEEL
tecoroute-0.1.0.dist-info/entry_points.txt
tecoroute-0.1.0.dist-info/top_level.txt
tecoroute-0.1.0.dist-info/zip-safe
tecoroute-0.1.0.dist-info/RECORD
