Metadata-Version: 2.1
Name: tecoroute
Version: 0.1.0
Summary: TecoRoute server and EPSNET connector.
Home-page: https://opensource.cze.tech/tecoroute
Author: Petr Czepiec
Author-email: petr@czepiec.me
Maintainer: Petr Czepiec
Maintainer-email: petr@czepiec.me
License: MIT
Project-URL: Source, https://github.com/czetech/tecoroute
Project-URL: Tracker, https://github.com/czetech/tecoroute/issues
Project-URL: Documentation, https://tecoroute.readthedocs.io/
Keywords: epsnet,tecoroute
Platform: UNKNOWN
Classifier: Development Status :: 5 - Production/Stable
Classifier: Environment :: Console
Classifier: Framework :: AsyncIO
Classifier: Intended Audience :: Information Technology
Classifier: Intended Audience :: Manufacturing
Classifier: License :: OSI Approved :: MIT License
Classifier: Natural Language :: English
Classifier: Operating System :: OS Independent
Classifier: Programming Language :: Python :: 3.8
Classifier: Programming Language :: Python :: 3.9
Classifier: Programming Language :: Python :: 3.10
Classifier: Topic :: Home Automation
Classifier: Topic :: System :: Hardware
Requires-Python: >=3.8
License-File: LICENSE
Requires-Dist: tornado (~=6.1)
Provides-Extra: uvloop
Requires-Dist: uvloop (~=0.16) ; extra == 'uvloop'
